pryzm/__init__.py
pryzm/codes.py
pryzm/pryzm.py
pryzm-0.1.4.dist-info/METADATA
pryzm-0.1.4.dist-info/WHEEL
pryzm-0.1.4.dist-info/top_level.txt
pryzm-0.1.4.dist-info/RECORD
