Metadata-Version: 2.1
Name: pryzm
Version: 0.1.4
Summary: Basic support for asci color text on linux terminals
Home-page: https://github.com/hydraseq/pryzm
Author: Efrain Olivares
Author-email: efrain.olivares@gmail.com
License: UNKNOWN
Platform: UNKNOWN
Classifier: Programming Language :: Python :: 3
Classifier: License :: OSI Approved :: MIT License
Classifier: Operating System :: OS Independent
